README.md
setup.py
trpc/__init__.py
trpc/client.py
trpc/server.py
trpc.egg-info/PKG-INFO
trpc.egg-info/SOURCES.txt
trpc.egg-info/dependency_links.txt
trpc.egg-info/requires.txt
trpc.egg-info/top_level.txt